curl2min/__init__.py
curl2min/cli.py
curl2min-0.0.4.dist-info/LICENSE
curl2min-0.0.4.dist-info/METADATA
curl2min-0.0.4.dist-info/WHEEL
curl2min-0.0.4.dist-info/entry_points.txt
curl2min-0.0.4.dist-info/top_level.txt
curl2min-0.0.4.dist-info/RECORD
