Metadata-Version: 2.1
Name: curl2min
Version: 0.0.4
Summary: Strip a curl statement down to it's essential arguments.
Author-email: fx2301 <realfx2301+pypi@gmail.com>
Project-URL: Homepage, https://github.com/fx2301/curl2min
Project-URL: Bug Tracker, https://github.com/fx2301/curl2min/issues
Classifier: Programming Language :: Python :: 3
Classifier: License :: OSI Approved :: MIT License
Classifier: Operating System :: OS Independent
Requires-Python: >=3.7
License-File: LICENSE
